<?xml version="1.0" encoding="UTF-8" standalone="yes"?>
<class>
    <cities>
        <city>
            <id>1</id>
            <name>Hồ Chí Minh</name>
            <description>Thành Phố Sầm Uất</description>
            <touristdestinations>
                <touristdestination>
                    <id>1</id>
                    <name>Pho Di Bo Nguyen Hue</name>
                    <description>Di Co  Gi Vui</description>
                    <img>url01</img>
                </touristdestination>
                <touristdestination>
                    <id>2</id>
                    <name>Pho Nguyen Hoa</name>
                    <description>Di Chua Nguoi Hoa</description>
                    <img>url02</img>
                </touristdestination>
                <touristdestination>
                    <id>3</id>
                    <name>HoConRua</name>
                    <description>Ngoi Chill Cung Ban</description>
                    <img>url03</img>
                </touristdestination>
            </touristdestinations>
        </city>
        <city>
            <id>2</id>
            <name>Ha Noi</name>
            <description>Thu Do</description>
            <touristdestinations>
                <touristdestination>
                    <id>4</id>
                    <name>Ho Ruom</name>
                    <description>Ngam Gai</description>
                    <img>url04</img>
                </touristdestination>
                <touristdestination>
                    <id>5</id>
                    <name>Pho Di Bo Ha Noi</name>
                    <description>Dancewithpeople</description>
                    <img>url05</img>
                </touristdestination>
                <touristdestination>
                    <id>6</id>
                    <name>Tran Duy Hung</name>
                    <description>Pho Di</description>
                    <img>url06</img>
                </touristdestination>
            </touristdestinations>
        </city>
        <city>
            <id>3</id>
            <name>Da Nang</name>
            <description>MienTrung</description>
            <touristdestinations>
                <touristdestination>
                    <id>7</id>
                    <name>Cau Rong</name>
                    <description>Phun Lua Phun Nuoc</description>
                    <img>url07</img>
                </touristdestination>
                <touristdestination>
                    <id>8</id>
                    <name>FPT Da Nang</name>
                    <description>truongdaihojc</description>
                    <img>url08</img>
                </touristdestination>
                <touristdestination>
                    <id>9</id>
                    <name>Co Do Hue</name>
                    <description>Hoi An</description>
                    <img>url9</img>
                </touristdestination>
            </touristdestinations>
        </city>
        <city>
            <id>4</id>
            <name>Demo Create</name>
            <description>Demo Create</description>
            <touristdestinations>
                <touristdestination>
                    <id>0</id>
                    <name>Demo create 1</name>
                    <description>Demo create</description>
                    <img>4</img>
                </touristdestination>
                <touristdestination>
                    <id>0</id>
                    <name>Demo create 2</name>
                    <description>Demo create</description>
                    <img>4</img>
                </touristdestination>
                <touristdestination>
                    <id>1</id>
                    <name>Demo create 3</name>
                    <description>Demo create</description>
                    <img>4</img>
                </touristdestination>
            </touristdestinations>
        </city>
    </cities>
    <tourtypes>
        <tourtype>
            <id>1</id>
            <name>Single</name>
            <description>Happy</description>
            <tours>
                <tour>
                    <id>1</id>
                    <name>Ho Chi Minh - Ha Noi i</name>
                    <startDate>10/10/2022</startDate>
                    <endDate>20/10/2022</endDate>
                    <days>10days</days>
                    <content>Yes</content>
                    <img>image</img>
                    <tourdeatils>
                        <tourdeatil>
                            <id>001</id>
                            <cityid>001</cityid>
                        </tourdeatil>
                        <tourdeatil>
                            <id>002</id>
                            <cityid>002</cityid>
                        </tourdeatil>
                        <tourdeatil>
                            <id>004</id>
                            <cityid>001</cityid>
                        </tourdeatil>
                        <tourdeatil>
                            <id>005</id>
                            <cityid>002</cityid>
                        </tourdeatil>
                        <tourdeatil>
                            <id>006</id>
                            <cityid>001</cityid>
                        </tourdeatil>
                        <tourdeatil>
                            <id>007</id>
                            <cityid>002</cityid>
                        </tourdeatil>
                    </tourdeatils>
                </tour>
            </tours>
        </tourtype>
        <tourtype>
            <id>2</id>
            <name>Family</name>
            <description>Bad</description>
            <tours>
                <tour>
                    <id>2</id>
                    <name>Ho Chi Minh - Ha Noi</name>
                    <startDate>01/10/2022</startDate>
                    <endDate>05/10/2022</endDate>
                    <days>4days</days>
                    <content>No</content>
                    <img>image</img>
                    <tourdeatils>
                        <tourdeatil>
                            <id>008</id>
                            <cityid>001</cityid>
                        </tourdeatil>
                        <tourdeatil>
                            <id>009</id>
                            <cityid>2</cityid>
                        </tourdeatil>
                        <tourdeatil>
                            <id>010</id>
                            <cityid>1</cityid>
                        </tourdeatil>
                        <tourdeatil>
                            <id>011</id>
                            <cityid>002</cityid>
                        </tourdeatil>
                        <tourdeatil>
                            <id>012</id>
                            <cityid>001</cityid>
                        </tourdeatil>
                        <tourdeatil>
                            <id>013</id>
                            <cityid>002</cityid>
                        </tourdeatil>
                    </tourdeatils>
                </tour>
            </tours>
        </tourtype>
        <tourtype>
            <id>3</id>
            <name>Couple Parent</name>
            <description>Đii đi vui lắm</description>
            <tours>
                <tour>
                    <id>3</id>
                    <name>Đà Lạt - Phan Thiếtt</name>
                    <startDate>5/11/2022</startDate>
                    <endDate>10/11/2022</endDate>
                    <days>5 days</days>
                    <content>Đi để đii luôn đi</content>
                    <img>url01</img>
                    <tourdeatils/>
                </tour>
                <tour>
                    <id>4</id>
                    <name>Đà Lạt - Phan Thiếtt 1</name>
                    <startDate>5/11/2022</startDate>
                    <endDate>10/11/2022</endDate>
                    <days>5 days</days>
                    <content>Đi để đii luôn đi</content>
                    <img>url01</img>
                    <tourdeatils/>
                </tour>
            </tours>
        </tourtype>
    </tourtypes>
</class>
